slimurl/__init__.py
slimurl/protocols.py
slimurl/url.py
slimurl-0.5.4.dist-info/DESCRIPTION.rst
slimurl-0.5.4.dist-info/METADATA
slimurl-0.5.4.dist-info/RECORD
slimurl-0.5.4.dist-info/WHEEL
slimurl-0.5.4.dist-info/metadata.json
slimurl-0.5.4.dist-info/top_level.txt
