Metadata-Version: 2.0
Name: slimurl
Version: 0.5.4
Summary: SlimURL - Fast library for parsing and building URL addresses
Home-page: UNKNOWN
Author: Dmitry Orlov <me@mosquito.su>
Author-email: me@mosquito.su
License: MIT
Platform: all
Classifier: Environment :: Console
Classifier: Programming Language :: Python
Classifier: Programming Language :: Python :: 2
Classifier: Programming Language :: Python :: 2.7
Classifier: Programming Language :: Python :: 3.1
Classifier: Programming Language :: Python :: 3.2
Classifier: Programming Language :: Python :: 3.4
Classifier: Programming Language :: Python :: 3.5
